{
    "fluentMethods": true,
    "clientRootFolder": "",
    "relationships": [
        {
            "relationshipName": "user",
            "otherEntityName": "user",
            "relationshipType": "many-to-one",
            "relationshipValidateRules": [
                "required"
            ],
            "otherEntityField": "login",
            "ownerSide": true,
            "otherEntityRelationshipName": "member",
            "otherEntityRelationshipNameUndefined": false
        }
    ],
    "fields": [
        {
            "fieldName": "expiresAt",
            "fieldType": "Instant"
        },
        {
            "fieldName": "type",
            "fieldType": "SourceType",
            "fieldValues": "WORKSPACE,PROJECT",
            "fieldValidateRules": [
                "required"
            ]
        },
        {
            "fieldName": "source",
            "fieldType": "Integer",
            "fieldValidateRules": [
                "required"
            ]
        },
        {
            "fieldName": "acessLevel",
            "fieldType": "AcessLevel",
            "fieldValues": "GUEST,CONTRIBUTOR,EDITOR,MANAGER,ADMIN",
            "fieldValidateRules": [
                "required"
            ]
        }
    ],
    "changelogDate": "20190326151334",
    "dto": "mapstruct",
    "searchEngine": false,
    "service": "serviceImpl",
    "entityTableName": "jhi_member",
    "databaseType": "sql",
    "jpaMetamodelFiltering": true,
    "pagination": "no",
    "enableEntityAudit": true
}
